Spork/__init__.py
Spork/basics.py
SporkLib-0.1.1.dist-info/LICENSE
SporkLib-0.1.1.dist-info/METADATA
SporkLib-0.1.1.dist-info/WHEEL
SporkLib-0.1.1.dist-info/top_level.txt
SporkLib-0.1.1.dist-info/RECORD
