Metadata-Version: 2.1
Name: SporkLib
Version: 0.1.1
Summary: A python package
Author-email: Boxei <knowing@mailfence.com>
Project-URL: Homepage, https://github.com/Boxei/Spork
Project-URL: Bug Tracker, https://github.com/Boxei/Spork/issues
Classifier: Programming Language :: Python :: 3
Classifier: License :: OSI Approved :: MIT License
Classifier: Operating System :: OS Independent
Requires-Python: >=3.7
License-File: LICENSE
